LICENSE
MANIFEST.in
README.md
setup.cfg
setup.py
django_mp_seo.egg-info/PKG-INFO
django_mp_seo.egg-info/SOURCES.txt
django_mp_seo.egg-info/dependency_links.txt
django_mp_seo.egg-info/top_level.txt
seo/__init__.py
seo/admin.py
seo/lib.py
seo/middleware.py
seo/models.py
seo/sitemaps.py
seo/translation.py
seo/urls.py
seo/views.py
seo/locale/ru/LC_MESSAGES/django.mo
seo/locale/ru/LC_MESSAGES/django.po
seo/locale/uk/LC_MESSAGES/django.mo
seo/locale/uk/LC_MESSAGES/django.po
seo/management/__init__.py
seo/management/commands/__init__.py
seo/management/commands/sync_page_meta.py
seo/migrations/0001_initial.py
seo/migrations/0002_auto_20190427_0832.py
seo/migrations/0003_auto_20190427_0906.py
seo/migrations/0004_auto_20190427_0953.py
seo/migrations/0005_auto_20190427_1001.py
seo/migrations/0006_pagemeta_og_image.py
seo/migrations/0007_search_query.py
seo/migrations/__init__.py
seo/templates/403.html
seo/templates/404.html
seo/templates/500.html
seo/templates/error.html
seo/templates/language_meta_tags.html
seo/templates/sitemap.html
seo/templates/sitemetrics/google.html
seo/templatetags/__init__.py
seo/templatetags/seo.py