Metadata-Version: 2.1
Name: django-mp-seo
Version: 9.0.3
Summary: Django seo app
Home-page: https://github.com/pmaigutyak/mp-seo
Author: Paul Maigutyak
Author-email: pmaigutyak@gmail.com
License: MIT
Download-URL: https://github.com/pmaigutyak/mp-seo/archive/9.0.3.tar.gz
Platform: UNKNOWN
License-File: LICENSE
